[
  {
    "id": "Neural-Rust",
    "name": "Neural-Rust",
    "description": "녹슨 닻으로 전선을 끊어내라",
    "artStyle": "일본 잉크 스플래쉬 스타일",
    "accent": "#005f73",
    "accentSub": "#0a9396",
    "tags": ["스팀펑크", "심해도시", "다크판타지", "로그라이크"],
    "synopsis": "Ai가 문명을 멸망 시킨지 102년 뒤, 우리는 거대한 톱니바퀴 선박에서 삶을 이어나간다.",
    "conceptNote": "잉크 효과라는 특이한 분위기의 독창적인 표현 기법을 사용해서 밀도 높은 세계관을 이야기한다.",
    "extraImages": [
      "/assets/worlds/Neural-Rust/gallery-01.webp"
    ]
  },
  {
    "id": "AsmoTherapy",
    "name": "AsmoTherapy",
    "description": "욕망을 마음껏 털어내고 가세요",
    "artStyle": "일본 수집형 RPG 스타일",
    "accent": "#7b2d8b",
    "accentSub": "#f4c430",
    "tags": ["서큐버스", "악마", "경영", "테라피"],
    "synopsis": "7대 죄악 중 하나인 색욕의 죄 아스모데우스가 운영하는 거대 사업체인 아스모테라피는 지금 이 순간에도 수천명의 욕망에 절여진 손님을 받는다.\n\n그곳에서 마주할 수 있는 것은 매력 넘치는 서큐버스들의 서비스.",
    "conceptNote": "노출도 있는 고퀄리티 일본풍 수집형 RPG스타일 그림체를 다양한 캐릭터로 매력있게 풀어냈다.",
    "extraImages": []
  },
  {
    "id": "판타지모험",
    "name": "판타지 모험",
    "description": "픽셀로 그린 모험의 서사",
    "artStyle": "픽셀풍",
    "accent": "#3a7d44",
    "accentSub": "#f9c74f",
    "tags": ["픽셀아트", "모험", "RPG", "판타지"],
    "synopsis": "세계의 끝, 열두 개의 현자 석이 흩어진 날부터 시대가 흔들리기 시작했다. 용사도 마왕도 없는 이 세계에서, 평범한 지도 제작자 소녀가 우연히 첫 번째 현자 석을 손에 넣는다.\n\n클래식 JRPG 문법을 픽셀아트로 재해석. '용사가 없는 세계의 모험'이라는 역설적 설정으로, 힘이 아닌 지식과 지도 제작 능력으로 문제를 해결하는 주인공을 중심에 둔다.",
    "conceptNote": "16×16 → 32×32 → 64×64 해상도를 세계관 내 '고대→현대→미래' 시대와 연결하는 메타 연출 시도. 초록과 황금 팔레트는 자연과 유물(relic)의 대비를 상징.",
    "extraImages": []
  }
]
